pt42api_wrapper/__init__.py
pt42api_wrapper/config.py
pt42api_wrapper/pt42api_token.py
pt42api_wrapper/pt42api_wrapper.py
pt42api_wrapper/utils.py
pt42api_wrapper-1.0.8.dist-info/METADATA
pt42api_wrapper-1.0.8.dist-info/WHEEL
pt42api_wrapper-1.0.8.dist-info/licenses/LICENSE
pt42api_wrapper-1.0.8.dist-info/RECORD
