Metadata-Version: 2.3
Name: pt42api_wrapper
Version: 1.0.8
Summary: A python package that simplifies the process of making API requests to 42 Portugal's API.
Project-URL: Homepage, https://github.com/42-Portugal/pt-api-wrapper
Project-URL: Issues, https://github.com/42-Portugal/pt-api-wrapper/issues
Author-email: 42 Portugal <root@42porto.com>
License-File: LICENSE
Classifier: License :: OSI Approved :: MIT License
Classifier: Operating System :: OS Independent
Classifier: Programming Language :: Python :: 3
Requires-Python: >=3.8
Requires-Dist: requests<2.32.0,>=2.31.0
